libdani/__init__.py
libdani/checkpoint/README.md
libdani/checkpoint/__init__.py
libdani/checkpoint/checkpoint.py
libdani/checkpoint/example.py
libdani-0.1.0.dist-info/METADATA
libdani-0.1.0.dist-info/WHEEL
libdani-0.1.0.dist-info/entry_points.txt
libdani-0.1.0.dist-info/licenses/LICENSE
libdani-0.1.0.dist-info/RECORD
