Metadata-Version: 2.4
Name: libdani
Version: 0.1.0
Summary: Add your description here
Author-email: Daniel Rodriguez <daniel@danielfrg.com>
License-Expression: WTFPL
License-File: LICENSE
Requires-Python: >=3.13
Requires-Dist: loguru>=0.7.3
